pytest_assertcount.py
pytest_assertcount-1.0.0.dist-info/LICENSE
pytest_assertcount-1.0.0.dist-info/METADATA
pytest_assertcount-1.0.0.dist-info/WHEEL
pytest_assertcount-1.0.0.dist-info/entry_points.txt
pytest_assertcount-1.0.0.dist-info/top_level.txt
pytest_assertcount-1.0.0.dist-info/RECORD
